[{"name": "ASIANPAINT", "fullname": "Asian Paints Ltd"}, {"name": "BAJAJ-AUTO", "fullname": "Bajaj Auto Ltd"}, {"name": "BEL", "fullname": "Bharat Electronics Ltd"}, {"name": "BHEL", "fullname": "Bhel"}, {"name": "CGPOWER", "fullname": "Cg Power And Ind Sol Ltd"}, {"name": "HAL", "fullname": "Hindustan Aeronautics Ltd"}, {"name": "HDFCBANK", "fullname": "Hdfc Bank Ltd"}, {"name": "HINDUNILVR", "fullname": "Hindustan Unilever Ltd"}, {"name": "ITC", "fullname": "Itc Ltd"}, {"name": "KOTAKBANK", "fullname": "Kotak Mahindra Bank Ltd"}, {"name": "MARUTI", "fullname": "Maruti Suzuki India Ltd"}, {"name": "MAZDOCK", "fullname": "Mazagon Dock Shipbuil Ltd"}, {"name": "NYKAA", "fullname": "Fsn E Commerce Ventures"}, {"name": "PAYTM", "fullname": "One 97 Communications Ltd"}, {"name": "SBIN", "fullname": "State Bank Of India"}, {"name": "SUZLON", "fullname": "Suzlon Energy Ltd"}, {"name": "SWIGGY", "fullname": "Swiggy Ltd"}, {"name": "TATAMOTORS", "fullname": "Tata Motors Ltd"}, {"name": "YESBANK", "fullname": "Yes Bank Ltd"}, {"name": "ZOMATO", "fullname": "Zomato Ltd"}]